odoo/addons/web_widget_text_count/README.rst
odoo/addons/web_widget_text_count/__init__.py
odoo/addons/web_widget_text_count/__manifest__.py
odoo/addons/web_widget_text_count/i18n/web_widget_text_count.pot
odoo/addons/web_widget_text_count/readme/CONTRIBUTORS.rst
odoo/addons/web_widget_text_count/readme/DESCRIPTION.rst
odoo/addons/web_widget_text_count/readme/ROADMAP.rst
odoo/addons/web_widget_text_count/readme/USAGE.rst
odoo/addons/web_widget_text_count/static/description/icon.png
odoo/addons/web_widget_text_count/static/description/index.html
odoo/addons/web_widget_text_count/static/src/js/fields_text_count.js
odoo/addons/web_widget_text_count/static/src/scss/field_text_count.scss
odoo/addons/web_widget_text_count/views/templates.xml
odoo12_addon_web_widget_text_count-12.0.1.0.0.99.dev2.dist-info/METADATA
odoo12_addon_web_widget_text_count-12.0.1.0.0.99.dev2.dist-info/WHEEL
odoo12_addon_web_widget_text_count-12.0.1.0.0.99.dev2.dist-info/top_level.txt
odoo12_addon_web_widget_text_count-12.0.1.0.0.99.dev2.dist-info/RECORD
